datedict/__init__.py
datedict/common.py
datedict/datedict.py
datedict/timedict.py
datedict/yeardict.py
datedict-1.0.11.dist-info/METADATA
datedict-1.0.11.dist-info/WHEEL
datedict-1.0.11.dist-info/licenses/LICENSE
datedict-1.0.11.dist-info/RECORD
