Metadata-Version: 2.4
Name: datedict
Version: 1.0.11
Summary: DateDict and YearDict: date-aware dictionary structures
Project-URL: Homepage, https://gitlab.com/grisus/datedict
Project-URL: Issues, https://gitlab.com/grisus/datedict/-/issues
Author-email: Lorenzo Guideri <lorenzo.guideri@dec-energy.ch>
License: MIT License
License-File: LICENSE
Classifier: License :: OSI Approved :: MIT License
Classifier: Operating System :: OS Independent
Classifier: Programming Language :: Python :: 3
Classifier: Typing :: Typed
Requires-Python: >=3.10
